README.md
setup.py
epoch/__init__.py
epoch/__main__.py
epoch/epoch.py
pyepoch.egg-info/PKG-INFO
pyepoch.egg-info/SOURCES.txt
pyepoch.egg-info/dependency_links.txt
pyepoch.egg-info/entry_points.txt
pyepoch.egg-info/not-zip-safe
pyepoch.egg-info/requires.txt
pyepoch.egg-info/top_level.txt