Metadata-Version: 2.1
Name: pyepoch
Version: 0.0.4
Summary: A simple python-based command-line utility to convert time or date stamps to epoch and back.
Home-page: https://github.com/0x3a/pyepoch
Author: Yonathan Klijnsma
Author-email: admin@0x3a.com
License: UNKNOWN
Platform: UNKNOWN
Requires-Python: >=3.3
